Workbook

Sheet Raw_Data
A1: Raw_Data – Source inputs (as reported)
A4: Bank | B4: Financial Year | C4: Reporting Basis | D4: ROA (%) | E4: ROE (%) | F4: NIM (%) | G4: GNPA (%) | H4: NNPA (%) | I4: Cost-to-Income (%) | J4: Advances (₹ crore) | K4: Deposits (₹ crore)
A5: HDFC Bank | B5: FY 2025-26 | C5: Standalone | D5: 1.94 | E5: 14.29 | F5: 3.5 | G5: 1.15 | H5: 0.38 | I5: 38 | J5: 2937166.3 | K5: 3105250.5
A6: ICICI Bank | B6: FY 2025-26 | C6: Standalone | D6: 2.32 | E6: 15.97 | F6: 4.32 | G6: 1.44 | H6: 0.35 | I6: 39.75 | J6: 1553892.9 | K6: 1794625
A7: State Bank of India (SBI) | B7: FY 2025-26 | C7: Standalone | D7: 1.12 | E7: 18.57 | F7: 2.91 | G7: 1.49 | H7: 0.39 | I7: 50.11 | J7: 4877894.8 | K7: 5975642.1

Sheet Analysis
A1: Analysis – Comparative KPI analysis
A4: A. KPI comparison and high / low values
A5: KPI | B5: Unit | C5: =Raw_Data!A5 -> HDFC Bank | D5: =Raw_Data!A6 -> ICICI Bank | E5: =Raw_Data!A7 -> State Bank of India (SBI) | F5: Highest reported | G5: Bank (highest) | H5: Lowest reported | I5: Bank (lowest) | J5: Tie check | K5: General interpretation (apply cautiously)
A6: Return on Assets (ROA) | B6: % | C6: =IF(ISNUMBER(Raw_Data!D5),Raw_Data!D5,"N/A") -> 1.94 | D6: =IF(ISNUMBER(Raw_Data!D6),Raw_Data!D6,"N/A") -> 2.32 | E6: =IF(ISNUMBER(Raw_Data!D7),Raw_Data!D7,"N/A") -> 1.12 | F6: =IF(COUNT(C6:E6)>=2,MAX(C6:E6),"N/A") -> 2.32 | G6: =IF(ISNUMBER(F6),INDEX($C$5:$E$5,MATCH(F6,C6:E6,0)),"N/A") -> ICICI Bank | H6: =IF(COUNT(C6:E6)>=2,MIN(C6:E6),"N/A") -> 1.12 | I6: =IF(ISNUMBER(H6),INDEX($C$5:$E$5,MATCH(H6,C6:E6,0)),"N/A") -> State Bank of India (SBI) | J6: =IF(ISNUMBER(F6),IF(COUNTIF(C6:E6,F6)>1,"Tie for highest (first bank shown)",IF(COUNTIF(C6:E6,H6)>1,"Tie for lowest (first bank shown)","No tie")),"N/A") -> No tie | K6: Higher = stronger reported asset profitability
A7: Return on Equity (ROE) | B7: % | C7: =IF(ISNUMBER(Raw_Data!E5),Raw_Data!E5,"N/A") -> 14.29 | D7: =IF(ISNUMBER(Raw_Data!E6),Raw_Data!E6,"N/A") -> 15.97 | E7: =IF(ISNUMBER(Raw_Data!E7),Raw_Data!E7,"N/A") -> 18.57 | F7: =IF(COUNT(C7:E7)>=2,MAX(C7:E7),"N/A") -> 18.57 | G7: =IF(ISNUMBER(F7),INDEX($C$5:$E$5,MATCH(F7,C7:E7,0)),"N/A") -> State Bank of India (SBI) | H7: =IF(COUNT(C7:E7)>=2,MIN(C7:E7),"N/A") -> 14.29 | I7: =IF(ISNUMBER(H7),INDEX($C$5:$E$5,MATCH(H7,C7:E7,0)),"N/A") -> HDFC Bank | J7: =IF(ISNUMBER(F7),IF(COUNTIF(C7:E7,F7)>1,"Tie for highest (first bank shown)",IF(COUNTIF(C7:E7,H7)>1,"Tie for lowest (first bank shown)","No tie")),"N/A") -> No tie | K7: Higher = stronger reported shareholder return (leverage matters)
A8: Net Interest Margin (NIM) | B8: % | C8: =IF(ISNUMBER(Raw_Data!F5),Raw_Data!F5,"N/A") -> 3.5 | D8: =IF(ISNUMBER(Raw_Data!F6),Raw_Data!F6,"N/A") -> 4.32 | E8: =IF(ISNUMBER(Raw_Data!F7),Raw_Data!F7,"N/A") -> 2.91 | F8: =IF(COUNT(C8:E8)>=2,MAX(C8:E8),"N/A") -> 4.32 | G8: =IF(ISNUMBER(F8),INDEX($C$5:$E$5,MATCH(F8,C8:E8,0)),"N/A") -> ICICI Bank | H8: =IF(COUNT(C8:E8)>=2,MIN(C8:E8),"N/A") -> 2.91 | I8: =IF(ISNUMBER(H8),INDEX($C$5:$E$5,MATCH(H8,C8:E8,0)),"N/A") -> State Bank of India (SBI) | J8: =IF(ISNUMBER(F8),IF(COUNTIF(C8:E8,F8)>1,"Tie for highest (first bank shown)",IF(COUNTIF(C8:E8,H8)>1,"Tie for lowest (first bank shown)","No tie")),"N/A") -> No tie | K8: Higher = stronger reported margin
A9: Gross NPA ratio (GNPA) | B9: % | C9: =IF(ISNUMBER(Raw_Data!G5),Raw_Data!G5,"N/A") -> 1.15 | D9: =IF(ISNUMBER(Raw_Data!G6),Raw_Data!G6,"N/A") -> 1.44 | E9: =IF(ISNUMBER(Raw_Data!G7),Raw_Data!G7,"N/A") -> 1.49 | F9: =IF(COUNT(C9:E9)>=2,MAX(C9:E9),"N/A") -> 1.49 | G9: =IF(ISNUMBER(F9),INDEX($C$5:$E$5,MATCH(F9,C9:E9,0)),"N/A") -> State Bank of India (SBI) | H9: =IF(COUNT(C9:E9)>=2,MIN(C9:E9),"N/A") -> 1.15 | I9: =IF(ISNUMBER(H9),INDEX($C$5:$E$5,MATCH(H9,C9:E9,0)),"N/A") -> HDFC Bank | J9: =IF(ISNUMBER(F9),IF(COUNTIF(C9:E9,F9)>1,"Tie for highest (first bank shown)",IF(COUNTIF(C9:E9,H9)>1,"Tie for lowest (first bank shown)","No tie")),"N/A") -> No tie | K9: Lower = better reported gross asset quality
A10: Net NPA ratio (NNPA) | B10: % | C10: =IF(ISNUMBER(Raw_Data!H5),Raw_Data!H5,"N/A") -> 0.38 | D10: =IF(ISNUMBER(Raw_Data!H6),Raw_Data!H6,"N/A") -> 0.35 | E10: =IF(ISNUMBER(Raw_Data!H7),Raw_Data!H7,"N/A") -> 0.39 | F10: =IF(COUNT(C10:E10)>=2,MAX(C10:E10),"N/A") -> 0.39 | G10: =IF(ISNUMBER(F10),INDEX($C$5:$E$5,MATCH(F10,C10:E10,0)),"N/A") -> State Bank of India (SBI) | H10: =IF(COUNT(C10:E10)>=2,MIN(C10:E10),"N/A") -> 0.35 | I10: =IF(ISNUMBER(H10),INDEX($C$5:$E$5,MATCH(H10,C10:E10,0)),"N/A") -> ICICI Bank | J10: =IF(ISNUMBER(F10),IF(COUNTIF(C10:E10,F10)>1,"Tie for highest (first bank shown)",IF(COUNTIF(C10:E10,H10)>1,"Tie for lowest (first bank shown)","No tie")),"N/A") -> No tie | K10: Lower = better reported net asset quality
A11: Cost-to-Income Ratio | B11: % | C11: =IF(ISNUMBER(Raw_Data!I5),Raw_Data!I5,"N/A") -> 38 | D11: =IF(ISNUMBER(Raw_Data!I6),Raw_Data!I6,"N/A") -> 39.75 | E11: =IF(ISNUMBER(Raw_Data!I7),Raw_Data!I7,"N/A") -> 50.11 | F11: =IF(COUNT(C11:E11)>=2,MAX(C11:E11),"N/A") -> 50.11 | G11: =IF(ISNUMBER(F11),INDEX($C$5:$E$5,MATCH(F11,C11:E11,0)),"N/A") -> State Bank of India (SBI) | H11: =IF(COUNT(C11:E11)>=2,MIN(C11:E11),"N/A") -> 38 | I11: =IF(ISNUMBER(H11),INDEX($C$5:$E$5,MATCH(H11,C11:E11,0)),"N/A") -> HDFC Bank | J11: =IF(ISNUMBER(F11),IF(COUNTIF(C11:E11,F11)>1,"Tie for highest (first bank shown)",IF(COUNTIF(C11:E11,H11)>1,"Tie for lowest (first bank shown)","No tie")),"N/A") -> No tie | K11: Lower = better reported efficiency (methodology differs) | L11: Broadly comparable; income/cost definitions differ slightly (see Sources).
A12: Advances | B12: ₹ crore | C12: =IF(ISNUMBER(Raw_Data!J5),Raw_Data!J5,"N/A") -> 2937166.3 | D12: =IF(ISNUMBER(Raw_Data!J6),Raw_Data!J6,"N/A") -> 1553892.9 | E12: =IF(ISNUMBER(Raw_Data!J7),Raw_Data!J7,"N/A") -> 4877894.8 | F12: =IF(COUNT(C12:E12)>=2,MAX(C12:E12),"N/A") -> 4877894.8 | G12: =IF(ISNUMBER(F12),INDEX($C$5:$E$5,MATCH(F12,C12:E12,0)),"N/A") -> State Bank of India (SBI) | H12: =IF(COUNT(C12:E12)>=2,MIN(C12:E12),"N/A") -> 1553892.9 | I12: =IF(ISNUMBER(H12),INDEX($C$5:$E$5,MATCH(H12,C12:E12,0)),"N/A") -> ICICI Bank | J12: =IF(ISNUMBER(F12),IF(COUNTIF(C12:E12,F12)>1,"Tie for highest (first bank shown)",IF(COUNTIF(C12:E12,H12)>1,"Tie for lowest (first bank shown)","No tie")),"N/A") -> No tie | K12: Higher = larger reported lending scale, not better performance | L12: Comparable: year-end net advances, standalone, ₹ crore.
A13: Deposits | B13: ₹ crore | C13: =IF(ISNUMBER(Raw_Data!K5),Raw_Data!K5,"N/A") -> 3105250.5 | D13: =IF(ISNUMBER(Raw_Data!K6),Raw_Data!K6,"N/A") -> 1794625 | E13: =IF(ISNUMBER(Raw_Data!K7),Raw_Data!K7,"N/A") -> 5975642.1 | F13: =IF(COUNT(C13:E13)>=2,MAX(C13:E13),"N/A") -> 5975642.1 | G13: =IF(ISNUMBER(F13),INDEX($C$5:$E$5,MATCH(F13,C13:E13,0)),"N/A") -> State Bank of India (SBI) | H13: =IF(COUNT(C13:E13)>=2,MIN(C13:E13),"N/A") -> 1794625 | I13: =IF(ISNUMBER(H13),INDEX($C$5:$E$5,MATCH(H13,C13:E13,0)),"N/A") -> ICICI Bank | J13: =IF(ISNUMBER(F13),IF(COUNTIF(C13:E13,F13)>1,"Tie for highest (first bank shown)",IF(COUNTIF(C13:E13,H13)>1,"Tie for lowest (first bank shown)","No tie")),"N/A") -> No tie | K13: Higher = larger reported deposit scale, not better performance | L13: Comparable: year-end total deposits, standalone, ₹ crore.
A16: B. Pairwise differences (first bank minus second bank; ratios in percentage points, balances in ₹ crore)
A17: KPI | B17: Unit | C17: HDFC − ICICI | D17: HDFC − SBI | E17: ICICI − SBI | F17: Comparability flag
A18: Return on Assets (ROA) | B18: pp | C18: =IF(AND(ISNUMBER(C6),ISNUMBER(D6)),C6-D6,"N/A") -> -0.38 | D18: =IF(AND(ISNUMBER(C6),ISNUMBER(E6)),C6-E6,"N/A") -> 0.82 | E18: =IF(AND(ISNUMBER(D6),ISNUMBER(E6)),D6-E6,"N/A") -> 1.2 | F18: OK – comparable basis
A19: Return on Equity (ROE) | B19: pp | C19: =IF(AND(ISNUMBER(C7),ISNUMBER(D7)),C7-D7,"N/A") -> -1.68 | D19: =IF(AND(ISNUMBER(C7),ISNUMBER(E7)),C7-E7,"N/A") -> -4.28 | E19: =IF(AND(ISNUMBER(D7),ISNUMBER(E7)),D7-E7,"N/A") -> -2.6 | F19: Caution – SBI ROE basis unconfirmed
A20: Net Interest Margin (NIM) | B20: pp | C20: =IF(AND(ISNUMBER(C8),ISNUMBER(D8)),C8-D8,"N/A") -> -0.82 | D20: =IF(AND(ISNUMBER(C8),ISNUMBER(E8)),C8-E8,"N/A") -> 0.59 | E20: =IF(AND(ISNUMBER(D8),ISNUMBER(E8)),D8-E8,"N/A") -> 1.41 | F20: WARNING – definitions differ/unconfirmed; indicative only
A21: Gross NPA ratio (GNPA) | B21: pp | C21: =IF(AND(ISNUMBER(C9),ISNUMBER(D9)),C9-D9,"N/A") -> -0.29 | D21: =IF(AND(ISNUMBER(C9),ISNUMBER(E9)),C9-E9,"N/A") -> -0.34 | E21: =IF(AND(ISNUMBER(D9),ISNUMBER(E9)),D9-E9,"N/A") -> -0.05 | F21: OK – comparable basis
A22: Net NPA ratio (NNPA) | B22: pp | C22: =IF(AND(ISNUMBER(C10),ISNUMBER(D10)),C10-D10,"N/A") -> 0.03 | D22: =IF(AND(ISNUMBER(C10),ISNUMBER(E10)),C10-E10,"N/A") -> -0.01 | E22: =IF(AND(ISNUMBER(D10),ISNUMBER(E10)),D10-E10,"N/A") -> -0.04 | F22: OK – comparable basis
A23: Cost-to-Income Ratio | B23: pp | C23: =IF(AND(ISNUMBER(C11),ISNUMBER(D11)),C11-D11,"N/A") -> -1.75 | D23: =IF(AND(ISNUMBER(C11),ISNUMBER(E11)),C11-E11,"N/A") -> -12.11 | E23: =IF(AND(ISNUMBER(D11),ISNUMBER(E11)),D11-E11,"N/A") -> -10.36 | F23: OK – comparable basis
A24: Advances | B24: ₹ crore | C24: =IF(AND(ISNUMBER(C12),ISNUMBER(D12)),C12-D12,"N/A") -> 1383273.3 | D24: =IF(AND(ISNUMBER(C12),ISNUMBER(E12)),C12-E12,"N/A") -> -1940728.6 | E24: =IF(AND(ISNUMBER(D12),ISNUMBER(E12)),D12-E12,"N/A") -> -3324001.9 | F24: OK – comparable basis
A25: Deposits | B25: ₹ crore | C25: =IF(AND(ISNUMBER(C13),ISNUMBER(D13)),C13-D13,"N/A") -> 1310625.5 | D25: =IF(AND(ISNUMBER(C13),ISNUMBER(E13)),C13-E13,"N/A") -> -2870391.6 | E25: =IF(AND(ISNUMBER(D13),ISNUMBER(E13)),D13-E13,"N/A") -> -4181017.1 | F25: OK – comparable basis
A28: C. Year-on-year growth in year-end balances (FY 2025-26 vs FY 2024-25, standalone) – Growth % = (Current − Prior) ÷ Prior × 100
A29: Bank | B29: Metric | C29: Prior (31 Mar 2025, ₹ crore) | D29: Current (31 Mar 2026, ₹ crore) | E29: Growth (%) | F29: Reconciliation to bank-reported growth
A30: HDFC Bank | B30: Advances | C30: =IF(ISNUMBER(#REF!),#REF!,"N/A") -> N/A | D30: =C12 -> 2937166.3 | E30: =IF(AND(ISNUMBER(C30),ISNUMBER(D30)),IF(C30<>0,(D30-C30)/C30*100,"N/A"),"N/A") -> N/A | F30: Bank-reported advances growth 12.1% (CEO message).
A31: HDFC Bank | B31: Deposits | C31: =IF(ISNUMBER(#REF!),#REF!,"N/A") -> N/A | D31: =C13 -> 3105250.5 | E31: =IF(AND(ISNUMBER(C31),ISNUMBER(D31)),IF(C31<>0,(D31-C31)/C31*100,"N/A"),"N/A") -> N/A | F31: Bank-reported deposit growth 14.4% (CEO message).
A32: ICICI Bank | B32: Advances | C32: =IF(ISNUMBER(#REF!),#REF!,"N/A") -> N/A | D32: =D12 -> 1553892.9 | E32: =IF(AND(ISNUMBER(C32),ISNUMBER(D32)),IF(C32<>0,(D32-C32)/C32*100,"N/A"),"N/A") -> N/A | F32: Bank-reported 15.8% for net advances net of BRDS/IBPC (MD&A); 14.1% on a gross-of-BRDS basis is a different measure.
A33: ICICI Bank | B33: Deposits | C33: =IF(ISNUMBER(#REF!),#REF!,"N/A") -> N/A | D33: =D13 -> 1794625 | E33: =IF(AND(ISNUMBER(C33),ISNUMBER(D33)),IF(C33<>0,(D33-C33)/C33*100,"N/A"),"N/A") -> N/A | F33: Bank-reported deposit growth 11.4% (MD&A).
A34: State Bank of India (SBI) | B34: Advances | C34: =IF(ISNUMBER(#REF!),#REF!,"N/A") -> N/A | D34: =E12 -> 4877894.8 | E34: =IF(AND(ISNUMBER(C34),ISNUMBER(D34)),IF(C34<>0,(D34-C34)/C34*100,"N/A"),"N/A") -> N/A | F34: Bank-reported advances growth 16.87% (KPI page) appears to use a different advances basis (₹49.3 trn).
A35: State Bank of India (SBI) | B35: Deposits | C35: =IF(ISNUMBER(#REF!),#REF!,"N/A") -> N/A | D35: =E13 -> 5975642.1 | E35: =IF(AND(ISNUMBER(C35),ISNUMBER(D35)),IF(C35<>0,(D35-C35)/C35*100,"N/A"),"N/A") -> N/A | F35: Bank-reported deposit growth 11.03% (Chairman's message).

Sheet Dashboard
B2: INDIAN BANKING FINANCIAL PERFORMANCE BENCHMARKING
B3: HDFC Bank | ICICI Bank | State Bank of India
S9: Chart data (formula-linked to Analysis; #N/A = missing, plotted as gap, never zero)
S10: Bank | T10: ROA (%) | U10: NIM (%) | V10: ROE (%) | W10: GNPA (%) | X10: NNPA (%) | Y10: Cost-to-Income (%) | Z10: Advances (₹ crore) | AA10: Deposits (₹ crore)
S11: HDFC | T11: =IF(ISNUMBER(Analysis!C6),Analysis!C6,NA()) -> 1.94 | U11: =IF(ISNUMBER(Analysis!C8),Analysis!C8,NA()) -> 3.5 | V11: =IF(ISNUMBER(Analysis!C7),Analysis!C7,NA()) -> 14.29 | W11: =IF(ISNUMBER(Analysis!C9),Analysis!C9,NA()) -> 1.15 | X11: =IF(ISNUMBER(Analysis!C10),Analysis!C10,NA()) -> 0.38 | Y11: =IF(ISNUMBER(Analysis!C11),Analysis!C11,NA()) -> 38 | Z11: =IF(ISNUMBER(Analysis!C12),Analysis!C12,NA()) -> 2937166.3 | AA11: =IF(ISNUMBER(Analysis!C13),Analysis!C13,NA()) -> 3105250.5
S12: ICICI | T12: =IF(ISNUMBER(Analysis!D6),Analysis!D6,NA()) -> 2.32 | U12: =IF(ISNUMBER(Analysis!D8),Analysis!D8,NA()) -> 4.32 | V12: =IF(ISNUMBER(Analysis!D7),Analysis!D7,NA()) -> 15.97 | W12: =IF(ISNUMBER(Analysis!D9),Analysis!D9,NA()) -> 1.44 | X12: =IF(ISNUMBER(Analysis!D10),Analysis!D10,NA()) -> 0.35 | Y12: =IF(ISNUMBER(Analysis!D11),Analysis!D11,NA()) -> 39.75 | Z12: =IF(ISNUMBER(Analysis!D12),Analysis!D12,NA()) -> 1553892.9 | AA12: =IF(ISNUMBER(Analysis!D13),Analysis!D13,NA()) -> 1794625
S13: SBI | T13: =IF(ISNUMBER(Analysis!E6),Analysis!E6,NA()) -> 1.12 | U13: =IF(ISNUMBER(Analysis!E8),Analysis!E8,NA()) -> 2.91 | V13: =IF(ISNUMBER(Analysis!E7),Analysis!E7,NA()) -> 18.57 | W13: =IF(ISNUMBER(Analysis!E9),Analysis!E9,NA()) -> 1.49 | X13: =IF(ISNUMBER(Analysis!E10),Analysis!E10,NA()) -> 0.39 | Y13: =IF(ISNUMBER(Analysis!E11),Analysis!E11,NA()) -> 50.11 | Z13: =IF(ISNUMBER(Analysis!E12),Analysis!E12,NA()) -> 4877894.8 | AA13: =IF(ISNUMBER(Analysis!E13),Analysis!E13,NA()) -> 5975642.1
B58: MY FINDINGS (formula-driven from Analysis and QA_Checks)
B59: =IF(COUNT(Analysis!C6:E8)=9,"Profitability – "&"ROA: highest "&Analysis!G6&" ("&TEXT(Analysis!F6,"0.00")&"%)"&", lowest "&Analysis!I6&" ("&TEXT(Analysis!H6,"0.00")&"%)"&". "&"ROE: highest "&Analysis!G7&" ("&TEXT(Analysis!F7,"0.00")&"%)"&", lowest "&Analysis!I7&" ("&TEXT(Analysis!H7,"0.00")&"%)"&". "&"NIM: highest "&Analysis!G8&" ("&TEXT(Analysis!F8,"0.00")&"%)"&", lowest "&Analysis!I8&" ("&TEXT(Analysis!H8,"0.00")&"%)"&". "&"Ranks differ by metric and NIM definitions are not identical, so no overall profitability leader is declared.","Profitability – insufficient comparable data; no reliable conclusion can be drawn.") -> Profitability – ROA: highest ICICI Bank (2.32%), lowest State Bank of India (SBI) (1.12%). ROE: highest State Bank of India (SBI) (18.57%), lowest HDFC Bank (14.29%). NIM: highest ICICI Bank (4.32%), lowest State Bank of India (SBI) (2.91%). Ranks differ by metric and NIM definitions are not identical, so no overall profitability leader is declared.
B60: =IF(COUNT(Analysis!C9:E10)=6,"Asset quality – "&"GNPA: highest "&Analysis!G9&" ("&TEXT(Analysis!F9,"0.00")&"%)"&", lowest "&Analysis!I9&" ("&TEXT(Analysis!H9,"0.00")&"%)"&". "&"NNPA: highest "&Analysis!G10&" ("&TEXT(Analysis!F10,"0.00")&"%)"&", lowest "&Analysis!I10&" ("&TEXT(Analysis!H10,"0.00")&"%)"&". "&"Lower ratios indicate better reported asset quality; ratios are standalone and on advances.","Asset quality – insufficient comparable data; no reliable conclusion can be drawn.") -> Asset quality – GNPA: highest State Bank of India (SBI) (1.49%), lowest HDFC Bank (1.15%). NNPA: highest State Bank of India (SBI) (0.39%), lowest ICICI Bank (0.35%). Lower ratios indicate better reported asset quality; ratios are standalone and on advances.
B61: =IF(COUNT(Analysis!C11:E11)=3,"Operating efficiency – "&"Cost-to-Income: highest "&Analysis!G11&" ("&TEXT(Analysis!F11,"0.00")&"%)"&", lowest "&Analysis!I11&" ("&TEXT(Analysis!H11,"0.00")&"%)"&". "&"Lower generally indicates better efficiency, subject to differing cost/income definitions.","Operating efficiency – insufficient comparable data; no reliable conclusion can be drawn.") -> Operating efficiency – Cost-to-Income: highest State Bank of India (SBI) (50.11%), lowest HDFC Bank (38.00%). Lower generally indicates better efficiency, subject to differing cost/income definitions.
B62: =IF(COUNT(Analysis!C12:E13)=6,"Advances and deposits – largest advances: "&Analysis!G12&" (₹"&TEXT(Analysis!F12,"#,##0")&" crore); largest deposits: "&Analysis!G13&" (₹"&TEXT(Analysis!F13,"#,##0")&" crore). Year-end standalone balances show scale, not performance.","Advances and deposits – insufficient comparable data; no reliable conclusion can be drawn.") -> Advances and deposits – largest advances: State Bank of India (SBI) (₹4,877,895 crore); largest deposits: State Bank of India (SBI) (₹5,975,642 crore). Year-end standalone balances show scale, not performance.
B63: ="Data comparability and verification – all three banks use "&Raw_Data!B5&" "&LOWER(Raw_Data!C5)&" figures. "&COUNTIF(#REF!,"Verified against PDF")&" of 24 observations are verified against the original PDF; "&COUNTIF(#REF!,"Partially verified")&" are partially verified (text-extract only). QA: "&COUNTIF(#REF!,"PASS")&" PASS, "&COUNTIF(#REF!,"WARNING")&" WARNING, "&COUNTIF(#REF!,"FAIL")&" FAIL. NIM definitions differ and SBI ROE/NIM bases are unconfirmed." -> #REF!
B65: Status definitions: 'Verified against PDF' requires inspection of the original PDF table; 'Partially verified' = traced to the report text extract and cross-checked but PDF page not inspected. Only 'Verified against PDF' counts toward the 24.
